faster_coco_eval-1.7.1.dist-info/WHEEL
faster_coco_eval-1.7.1.dist-info/top_level.txt
faster_coco_eval-1.7.1.dist-info/METADATA
faster_coco_eval-1.7.1.dist-info/RECORD
faster_coco_eval-1.7.1.dist-info/licenses/LICENSE
faster_coco_eval-1.7.1.data/data/extra.txt
faster_coco_eval-1.7.1.data/data/docs.txt
faster_coco_eval-1.7.1.data/data/tests.txt
faster_coco_eval-1.7.1.data/data/runtime.txt
faster_coco_eval/version.py
faster_coco_eval/mask_api_new_cpp.cpython-310-aarch64-linux-gnu.so
faster_coco_eval/__init__.py
faster_coco_eval/faster_eval_api_cpp.cpython-310-aarch64-linux-gnu.so
faster_coco_eval/utils/__init__.py
faster_coco_eval/utils/pytorch/coco_dataset.py
faster_coco_eval/utils/pytorch/__init__.py
faster_coco_eval/utils/pytorch/coco_eval.py
faster_coco_eval/extra/utils.py
faster_coco_eval/extra/extra.py
faster_coco_eval/extra/display.py
faster_coco_eval/extra/draw.py
faster_coco_eval/extra/__init__.py
faster_coco_eval/extra/curves.py
faster_coco_eval/core/faster_eval_api.py
faster_coco_eval/core/coco.py
faster_coco_eval/core/__init__.py
faster_coco_eval/core/cocoeval.py
faster_coco_eval/core/mask.py
