Metadata-Version: 2.1
Name: faster-coco-eval
Version: 1.7.1
Summary: Faster interpretation of the original COCOEval
Home-page: https://github.com/MiXaiLL76/faster_coco_eval
Author: MiXaiLL76
Author-email: mike.milos@yandex.ru
Classifier: Development Status :: 4 - Beta
Classifier: Operating System :: OS Independent
Classifier: Programming Language :: Python :: 3
Classifier: Programming Language :: Python :: 3.7
Classifier: Programming Language :: Python :: 3.8
Classifier: Programming Language :: Python :: 3.9
Classifier: Programming Language :: Python :: 3.10
Classifier: Programming Language :: Python :: 3.11
Classifier: Programming Language :: Python :: 3.12
Classifier: Programming Language :: Python :: 3.13
Classifier: Topic :: Scientific/Engineering :: Artificial Intelligence
Requires-Python: >=3.7
License-File: LICENSE
Requires-Dist: numpy
Provides-Extra: extra
Requires-Dist: numpy ; extra == 'extra'
Requires-Dist: opencv-python-headless ; extra == 'extra'
Requires-Dist: pandas ; extra == 'extra'
Requires-Dist: plotly ; extra == 'extra'
Requires-Dist: Pillow ; extra == 'extra'
Provides-Extra: tests
Requires-Dist: numpy ; extra == 'tests'
Requires-Dist: pytest ; extra == 'tests'
Requires-Dist: pytest-cov ; extra == 'tests'
Requires-Dist: parameterized ; extra == 'tests'
Requires-Dist: pycocotools ; (python_version < "3.13") and extra == 'tests'
